odoo/addons/website_event_no_index/README.rst
odoo/addons/website_event_no_index/__init__.py
odoo/addons/website_event_no_index/__manifest__.py
odoo/addons/website_event_no_index/i18n/it.po
odoo/addons/website_event_no_index/i18n/website_event_no_index.pot
odoo/addons/website_event_no_index/readme/CONTRIBUTORS.md
odoo/addons/website_event_no_index/readme/DESCRIPTION.md
odoo/addons/website_event_no_index/static/description/icon.png
odoo/addons/website_event_no_index/static/description/icon.svg
odoo/addons/website_event_no_index/static/description/index.html
odoo/addons/website_event_no_index/views/website_templates.xml
odoo14_addon_website_event_no_index-14.0.1.0.1.dev3.dist-info/METADATA
odoo14_addon_website_event_no_index-14.0.1.0.1.dev3.dist-info/WHEEL
odoo14_addon_website_event_no_index-14.0.1.0.1.dev3.dist-info/top_level.txt
odoo14_addon_website_event_no_index-14.0.1.0.1.dev3.dist-info/RECORD
